weka_porter/__init__.py
weka_porter/__main__.py
weka_porter-0.1.0.dist-info/DESCRIPTION.rst
weka_porter-0.1.0.dist-info/METADATA
weka_porter-0.1.0.dist-info/RECORD
weka_porter-0.1.0.dist-info/WHEEL
weka_porter-0.1.0.dist-info/metadata.json
weka_porter-0.1.0.dist-info/top_level.txt
