Metadata-Version: 2.0
Name: weka-porter
Version: 0.1.0
Summary: Transpile trained decision trees from Weka to a low-level programming language.
Home-page: https://github.com/nok/weka-porter/tree/stable
Author: Darius Morawiec
Author-email: ping@nok.onl
License: MIT
Keywords: weka,decision-tree
Platform: UNKNOWN
Classifier: Programming Language :: Python :: 2
Classifier: Programming Language :: Python :: 2.7
Classifier: Programming Language :: Python :: 3
Classifier: Programming Language :: Python :: 3.2
Classifier: Programming Language :: Python :: 3.3
Classifier: Programming Language :: Python :: 3.4
Classifier: Programming Language :: Python :: 3.5
Requires-Dist: args (==0.1.0)
Requires-Dist: clint (==0.5.1)
Requires-Dist: pkginfo (==1.4.1)
Requires-Dist: requests (==2.12.1)
Requires-Dist: requests-toolbelt (==0.7.0)
Requires-Dist: six (==1.10.0)
Requires-Dist: twine (==1.8.1)
Requires-Dist: wheel (==0.29.0)
